[
  {
    "action": "default",
    "active": true,
    "description": "New Flow Control Notes and Remarks",
    "exclude": [],
    "id": "c03dabe4b9ca",
    "include": [
      "all"
    ],
    "key": [
      {
        "attrs": "ip"
      }
    ],
    "name": "Flow Control Policy Example",
    "sequence": [
      {
        "args": {},
        "cookies": {},
        "headers": {
          "host": "www.example.com"
        },
        "method": "GET",
        "uri": "/login"
      },
      {
        "args": {},
        "cookies": {},
        "headers": {
          "host": "www.example.com"
        },
        "method": "POST",
        "uri": "/login"
      }
    ],
    "timeframe": 60
  }
]
